django_twilio_sms/views.py
django_twilio_sms/urls.py
django_twilio_sms/models.py
django_twilio_sms/apps.py
django_twilio_sms/admin.py
django_twilio_sms/signals.py
django_twilio_sms/__init__.py
django_twilio_sms/utils.py
django_twilio_sms/management/__init__.py
django_twilio_sms/management/commands/sync_responses.py
django_twilio_sms/management/commands/__init__.py
django_twilio_sms/migrations/0001_squashed_0005_auto_20160410_1948.py
django_twilio_sms/migrations/__init__.py
django_twilio_sms/migrations/0002_auto_20160512_2117.py
django_twilio_sms_models-1.2.0.dist-info/WHEEL
django_twilio_sms_models-1.2.0.dist-info/METADATA
django_twilio_sms_models-1.2.0.dist-info/top_level.txt
django_twilio_sms_models-1.2.0.dist-info/RECORD
django_twilio_sms_models-1.2.0.dist-info/DESCRIPTION.rst
django_twilio_sms_models-1.2.0.dist-info/metadata.json
