Metadata-Version: 2.0
Name: django-twilio-sms-models
Version: 1.2.0
Summary: Django models for Twilio's Programmable SMS
Home-page: https://github.com/cfc603/django-twilio-sms-models
Author: Trevor Watson
Author-email: trevor@trevorwatson.me
License: BSD
Keywords: django-twilio-sms-models
Platform: UNKNOWN
Classifier: Development Status :: 3 - Alpha
Classifier: Framework :: Django
Classifier: Framework :: Django :: 1.8
Classifier: Framework :: Django :: 1.9
Classifier: Intended Audience :: Developers
Classifier: License :: OSI Approved :: BSD License
Classifier: Natural Language :: English
Classifier: Programming Language :: Python :: 2
Classifier: Programming Language :: Python :: 2.7
Classifier: Programming Language :: Python :: 3
Classifier: Programming Language :: Python :: 3.3
Classifier: Programming Language :: Python :: 3.4
Classifier: Programming Language :: Python :: 3.5
Requires-Dist: twilio (>=5.4.0)
Requires-Dist: Django (>=1.8.0)
Requires-Dist: django-twilio (>=0.8.0)
Requires-Dist: django-phonenumber-field (>=1.1.0)
